gpflow_lfm/__init__.py
gpflow_lfm-0.0.1.dist-info/LICENSE
gpflow_lfm-0.0.1.dist-info/METADATA
gpflow_lfm-0.0.1.dist-info/WHEEL
gpflow_lfm-0.0.1.dist-info/top_level.txt
gpflow_lfm-0.0.1.dist-info/RECORD
